obsws_cli/__about__.py
obsws_cli/__init__.py
obsws_cli/alias.py
obsws_cli/app.py
obsws_cli/console.py
obsws_cli/envconfig.py
obsws_cli/protocols.py
obsws_cli/styles.py
obsws_cli/util.py
obsws_cli/validate.py
obsws_cli/commands/filter.py
obsws_cli/commands/group.py
obsws_cli/commands/hotkey.py
obsws_cli/commands/input.py
obsws_cli/commands/media.py
obsws_cli/commands/profile.py
obsws_cli/commands/projector.py
obsws_cli/commands/record.py
obsws_cli/commands/replaybuffer.py
obsws_cli/commands/scene.py
obsws_cli/commands/scenecollection.py
obsws_cli/commands/sceneitem.py
obsws_cli/commands/screenshot.py
obsws_cli/commands/settings.py
obsws_cli/commands/stream.py
obsws_cli/commands/studiomode.py
obsws_cli/commands/text.py
obsws_cli/commands/virtualcam.py
obsws_cli-0.24.6.dist-info/METADATA
obsws_cli-0.24.6.dist-info/WHEEL
obsws_cli-0.24.6.dist-info/entry_points.txt
obsws_cli-0.24.6.dist-info/licenses/LICENSE.txt
obsws_cli-0.24.6.dist-info/RECORD
