Metadata-Version: 2.4
Name: obsws-cli
Version: 0.24.6
Summary: A command line interface for the OBS WebSocket API.
Project-URL: Documentation, https://github.com/onyx-and-iris/obsws-cli#readme
Project-URL: Issues, https://github.com/onyx-and-iris/obsws-cli/issues
Project-URL: Source, https://github.com/onyx-and-iris/obsws-cli
Author-email: onyx-and-iris <code@onyxandiris.online>
License-Expression: MIT
License-File: LICENSE.txt
Keywords: cli,command-line,obs,obs-websocket,obs-websocket-api
Classifier: Development Status :: 4 - Beta
Classifier: Programming Language :: Python
Classifier: Programming Language :: Python :: 3.10
Classifier: Programming Language :: Python :: 3.11
Classifier: Programming Language :: Python :: 3.12
Classifier: Programming Language :: Python :: 3.13
Classifier: Programming Language :: Python :: Implementation :: CPython
Classifier: Programming Language :: Python :: Implementation :: PyPy
Requires-Python: >=3.10
Requires-Dist: obsws-python>=1.8.0
Requires-Dist: python-dotenv>=1.1.0
Requires-Dist: typer>=0.21.1
